{
    "type": "data",
    "nodes": [
      {
        "type": "data",
        "data": [
          {
            "session": -1,
            "cookies": 1,
            "loc": 11,
            "theme": -1,
            "hideNewsSources": 15,
            "ab": 16
          },
          [
            2,
            5,
            8
          ],
          {
            "name": 3,
            "value": 4
          },
          "_ga_C83MWM65QF",
          "GS1.1.1695719710.2.1.1695719773.0.0.0",
          {
            "name": 6,
            "value": 7
          },
          "_ga",
          "GA1.1.1985740954.1694588654",
          {
            "name": 9,
            "value": 10
          },
          "_ga_ZVM14ND8J8",
          "GS1.1.1728801502.9.1.1728804109.0.0.0",
          {
            "co": 12,
            "isUS": 13,
            "isEU": 14,
            "isCA": 13
          },
          "GR",
          false,
          true,
          [],
          {}
        ],
        "uses": {},
        "slash": "always"
      },
      {
        "type": "data",
        "data": [
          {
            "info": 1
          },
          {
            "type": 2,
            "symbol": 3,
            "ticker": 4,
            "name": 5,
            "nameFull": 6,
            "exchange": 7,
            "baseurl": 8,
            "quote": 9,
            "state": 36,
            "archived": 37,
            "notice": 38,
            "ipoDate": 39,
            "cik": 40,
            "id": 41,
            "curr": 42,
            "stream": 15,
            "uid": 34,
            "template": 44,
            "features": 45
          },
          "stocks",
          "aapl",
          "AAPL",
          "Apple",
          "Apple Inc.",
          "NASDAQ",
          "/stocks/aapl",
          {
            "c": 10,
            "cdr": 11,
            "cl": 12,
            "cp": 13,
            "days": 14,
            "e": 15,
            "ec": 16,
            "ecp": 17,
            "ep": 18,
            "epd": 18,
            "es": 19,
            "ets": 20,
            "eu": 21,
            "ex": 7,
            "exp": 22,
            "h": 23,
            "h52": 24,
            "l": 25,
            "l52": 26,
            "mc": 27,
            "ms": 28,
            "o": 29,
            "p": 30,
            "pd": 30,
            "symbol": 3,
            "td": 31,
            "ts": 32,
            "u": 33,
            "uid": 34,
            "v": 35
          },
          -1.49,
          -1,
          229.04,
          -0.65,
          0,
          true,
          -0.15,
          -0.07,
          227.4,
          "After-hours",
          1728691192102,
          "Oct 11, 2024, 7:59 PM EDT",
          1728893700000,
          229.41,
          237.23,
          227.34,
          164.08,
          3443880691000,
          "closed",
          229.3,
          227.55,
          "2024-10-11",
          1728676801000,
          "Oct 11, 2024, 4:00 PM",
          "stocks/AAPL",
          30817675,
          "normal",
          false,
          null,
          "1980-12-12",
          "0000320193",
          "recC21YRS88bfCq3t",
          {
            "dividend": 43,
            "financial": 43,
            "main": 43,
            "price": 43
          },
          "USD",
          "Standard",
          {
            "chart": 15,
            "dividend": 15,
            "employees": 15,
            "financials": 15,
            "forecast": 15,
            "history": 15,
            "market_cap": 15,
            "metrics": 15,
            "revenue": 15
          }
        ],
        "uses": {
          "params": [
            "symbol"
          ]
        }
      },
      {
        "type": "data",
        "data": [
          {
            "estimates": 1,
            "estimatesCharts": 145,
            "targets": 187,
            "recommendations": 256,
            "ratings": 324,
            "meta": 400
          },
          {
            "stats": 2,
            "table": 35
          },
          {
            "annual": 3,
            "quarterly": 18
          },
          {
            "epsNext": 4,
            "epsThis": 8,
            "revenueNext": 11,
            "revenueThis": 15
          },
          {
            "growth": 5,
            "last": 6,
            "this": 7
          },
          11.550987222425277,
          6.837213,
          7.6269786,
          {
            "growth": 9,
            "last": 10,
            "this": 6
          },
          11.53691680261012,
          6.13,
          {
            "growth": 12,
            "last": 13,
            "this": 14
          },
          8.02200010045708,
          398180000000,
          430122000000,
          {
            "growth": 16,
            "last": 17,
            "this": 13
          },
          3.8861421657513335,
          383285000000,
          {
            "epsNext": 19,
            "epsThis": 23,
            "revenueNext": 27,
            "revenueThis": 31
          },
          {
            "growth": 20,
            "last": 21,
            "this": 22
          },
          8.715623853211001,
          2.18,
          2.3700006,
          {
            "growth": 24,
            "last": 25,
            "this": 26
          },
          9.868093082545482,
          1.459135,
          1.6031238,
          {
            "growth": 28,
            "last": 29,
            "this": 30
          },
          8.313610704578716,
          119575000000,
          129516000000,
          {
            "growth": 32,
            "last": 33,
            "this": 34
          },
          7.587879058749916,
          89498000000,
          96289000000,
          {
            "annual": 36,
            "quarterly": 91
          },
          {
            "analysts": 37,
            "dates": 42,
            "eps": 53,
            "epsGrowth": 59,
            "fiscalYear": 66,
            "lastDate": 77,
            "revenue": 78,
            "revenueGrowth": 84
          },
          [
            38,
            38,
            38,
            38,
            38,
            39,
            39,
            40,
            41,
            41
          ],
          null,
          46,
          28,
          "[PRO]",
          [
            43,
            44,
            45,
            46,
            47,
            48,
            49,
            50,
            51,
            52
          ],
          "2019-09-28",
          "2020-09-26",
          "2021-09-25",
          "2022-09-24",
          "2023-09-30",
          "2024-09-30",
          "2025-09-30",
          "2026-09-30",
          "2027-09-30",
          "2028-09-30",
          [
            54,
            55,
            56,
            57,
            10,
            6,
            7,
            58,
            41,
            41
          ],
          2.97,
          3.28,
          5.61,
          6.11,
          8.5706214,
          [
            60,
            61,
            62,
            63,
            64,
            9,
            5,
            65,
            41,
            41
          ],
          -0.3355704697986517,
          10.437710437710424,
          71.03658536585368,
          8.912655971479499,
          0.3273322422258529,
          12.372432774362316,
          [
            67,
            68,
            69,
            70,
            71,
            72,
            73,
            74,
            75,
            76
          ],
          "2019",
          "2020",
          "2021",
          "2022",
          "2023",
          "2024",
          "2025",
          "2026",
          "2027",
          "2028",
          4,
          [
            79,
            80,
            81,
            82,
            17,
            13,
            14,
            83,
            41,
            41
          ],
          260174000000,
          274515000000,
          365817000000,
          394328000000,
          463918000000,
          [
            85,
            86,
            87,
            88,
            89,
            16,
            12,
            90,
            41,
            41
          ],
          -2.04107758052674,
          5.512080376978479,
          33.259384733074704,
          7.79378760418461,
          -2.800460530319937,
          7.8573056016665035,
          {
            "analysts": 92,
            "dates": 96,
            "eps": 107,
            "epsGrowth": 114,
            "fiscalQuarter": 123,
            "fiscalYear": 128,
            "lastDate": 77,
            "revenue": 129,
            "revenueGrowth": 136
          },
          [
            38,
            38,
            38,
            38,
            38,
            93,
            94,
            95,
            95,
            95,
            41,
            41,
            41,
            41
          ],
          30,
          19,
          15,
          [
            97,
            47,
            98,
            99,
            100,
            48,
            101,
            102,
            103,
            49,
            104,
            105,
            106,
            50
          ],
          "2023-07-01",
          "2023-12-30",
          "2024-03-30",
          "2024-06-29",
          "2024-12-31",
          "2025-03-31",
          "2025-06-30",
          "2025-12-31",
          "2026-03-31",
          "2026-06-30",
          [
            108,
            25,
            21,
            109,
            110,
            26,
            22,
            111,
            112,
            113,
            41,
            41,
            41,
            41
          ],
          1.26,
          1.53,
          1.4,
          1.6938324,
          1.5073254,
          1.7344692000000002,
          [
            115,
            116,
            117,
            118,
            119,
            24,
            20,
            120,
            121,
            122,
            41,
            41,
            41,
            41
          ],
          5.000000000000004,
          13.469593118111,
          15.957446808510657,
          0.6578947368421018,
          11.111111111111093,
          10.708,
          7.666100000000009,
          8.193091512957393,
          [
            124,
            125,
            126,
            127,
            124,
            125,
            126,
            127,
            124,
            125,
            126,
            127,
            124,
            125
          ],
          "Q3",
          "Q4",
          "Q1",
          "Q2",
          [
            71,
            71,
            72,
            72,
            72,
            72,
            73,
            73,
            73,
            73,
            74,
            74,
            74,
            74
          ],
          [
            130,
            33,
            29,
            131,
            132,
            34,
            30,
            133,
            134,
            135,
            41,
            41,
            41,
            41
          ],
          81797000000,
          90753000000,
          85777000000,
          98788000000,
          91714000000,
          100885000000,
          [
            137,
            138,
            139,
            140,
            141,
            32,
            28,
            142,
            143,
            144,
            41,
            41,
            41,
            41
          ],
          -1.400691908050966,
          -0.7188338916868209,
          2.066510746538741,
          -4.305327090978106,
          4.865704121178038,
          8.853701806000904,
          6.921435816127866,
          4.773130887224917,
          {
            "eps": 146,
            "epsGrowth": 156,
            "revenue": 166,
            "revenueGrowth": 177
          },
          {
            "2024-09-30": 147,
            "2025-09-30": 150,
            "2026-09-30": 153,
            "2027-09-30": 41,
            "2028-09-30": 41
          },
          {
            "avg": 6,
            "high": 148,
            "low": 149,
            "no": 39
          },
          7.0875,
          6.4386,
          {
            "avg": 7,
            "high": 151,
            "low": 152,
            "no": 39
          },
          8.4,
          6.7424,
          {
            "avg": 58,
            "high": 154,
            "low": 155,
            "no": 40
          },
          10.185,
          7.0854,
          {
            "2024-09-30": 157,
            "2025-09-30": 160,
            "2026-09-30": 163,
            "2027-09-30": 41,
            "2028-09-30": 41
          },
          {
            "avg": 9,
            "high": 158,
            "low": 159
          },
          15.619902120717787,
          5.034257748776513,
          {
            "avg": 5,
            "high": 161,
            "low": 162
          },
          22.857076414030104,
          -1.3867199983385081,
          {
            "avg": 65,
            "high": 164,
            "low": 165
          },
          33.53911862293675,
          -7.100827580662155,
          {
            "2024-09-30": 167,
            "2025-09-30": 171,
            "2026-09-30": 174,
            "2027-09-30": 41,
            "2028-09-30": 41
          },
          {
            "avg": 13,
            "high": 168,
            "low": 169,
            "no": 170
          },
          413753000000,
          379375000000,
          45,
          {
            "avg": 14,
            "high": 172,
            "low": 173,
            "no": 170
          },
          463976000000,
          393657000000,
          {
            "avg": 83,
            "high": 175,
            "low": 176,
            "no": 93
          },
          523535000000,
          405578000000,
          {
            "2024-09-30": 178,
            "2025-09-30": 181,
            "2026-09-30": 184,
            "2027-09-30": 41,
            "2028-09-30": 41
          },
          {
            "avg": 16,
            "high": 179,
            "low": 180
          },
          7.949176200477452,
          -1.0201286249135761,
          {
            "avg": 12,
            "high": 182,
            "low": 183
          },
          16.524185041940832,
          -1.1359184288512731,
          {
            "avg": 90,
            "high": 185,
            "low": 186
          },
          21.71779169630942,
          -5.706287983409358,
          {
            "average": 188,
            "count": 189,
            "filtered": 190,
            "high": 193,
            "low": 194,
            "median": 195,
            "updated": 196,
            "chart": 214
          },
          240.71,
          31,
          {
            "1": 191,
            "2": 197,
            "3": 201,
            "4": 204,
            "5": 207
          },
          {
            "average": 192,
            "count": 93,
            "high": 193,
            "low": 194,
            "median": 195,
            "updated": 196
          },
          239.56,
          300,
          180,
          250,
          "2024-10-09",
          {
            "average": 198,
            "count": 199,
            "high": 193,
            "low": 200,
            "median": 195,
            "updated": 196
          },
          244.08,
          24,
          186,
          {
            "average": 202,
            "count": 203,
            "high": 193,
            "low": 200,
            "median": 195,
            "updated": 196
          },
          246.82,
          22,
          {
            "average": 205,
            "count": 94,
            "high": 193,
            "low": 200,
            "median": 195,
            "updated": 206
          },
          247.47,
          "2024-10-03",
          {
            "average": 208,
            "count": 209,
            "high": 210,
            "low": 211,
            "median": 212,
            "updated": 213
          },
          229.67,
          6,
          255,
          203,
          240,
          "2024-09-25",
          [
            215,
            218,
            221,
            224,
            227,
            230,
            233,
            236,
            239,
            242,
            245,
            248,
            251,
            254
          ],
          {
            "t": 216,
            "c": 217
          },
          "2023-10-01",
          170.77,
          {
            "t": 219,
            "c": 220
          },
          "2023-11-01",
          189.95,
          {
            "t": 222,
            "c": 223
          },
          "2023-12-01",
          192.53,
          {
            "t": 225,
            "c": 226
          },
          "2024-01-01",
          184.4,
          {
            "t": 228,
            "c": 229
          },
          "2024-02-01",
          180.75,
          {
            "t": 231,
            "c": 232
          },
          "2024-03-01",
          171.48,
          {
            "t": 234,
            "c": 235
          },
          "2024-04-01",
          170.33,
          {
            "t": 237,
            "c": 238
          },
          "2024-05-01",
          192.25,
          {
            "t": 240,
            "c": 241
          },
          "2024-06-01",
          210.62,
          {
            "t": 243,
            "c": 244
          },
          "2024-07-01",
          222.08,
          {
            "t": 246,
            "c": 247
          },
          "2024-08-01",
          229,
          {
            "t": 249,
            "c": 250
          },
          "2024-09-01",
          233,
          {
            "t": 252,
            "c": 253
          },
          "2024-10-01",
          227.55,
          {
            "t": 255,
            "c": 38
          },
          "2025-10-13",
          [
            257,
            268,
            272,
            276,
            281,
            288,
            294,
            298,
            303,
            309,
            314,
            319,
            321
          ],
          {
            "date": 258,
            "month": 259,
            "strongBuy": 260,
            "buy": 261,
            "hold": 262,
            "sell": 263,
            "strongSell": 264,
            "consensus": 265,
            "score": 266,
            "total": 267,
            "updated": 258
          },
          "2023-10-31",
          "Oct '23",
          11,
          13,
          10,
          0,
          1,
          "Buy",
          4.71,
          35,
          {
            "date": 269,
            "month": 270,
            "strongBuy": 260,
            "buy": 261,
            "hold": 262,
            "sell": 263,
            "strongSell": 264,
            "consensus": 265,
            "score": 266,
            "total": 267,
            "updated": 271
          },
          "2023-11-30",
          "Nov '23",
          "2023-11-24",
          {
            "date": 273,
            "month": 274,
            "strongBuy": 260,
            "buy": 261,
            "hold": 262,
            "sell": 263,
            "strongSell": 264,
            "consensus": 265,
            "score": 266,
            "total": 267,
            "updated": 275
          },
          "2023-12-31",
          "Dec '23",
          "2023-12-20",
          {
            "date": 277,
            "month": 278,
            "strongBuy": 279,
            "buy": 260,
            "hold": 262,
            "sell": 264,
            "strongSell": 264,
            "consensus": 265,
            "score": 280,
            "total": 267,
            "updated": 277
          },
          "2024-01-31",
          "Jan '24",
          12,
          4.57,
          {
            "date": 282,
            "month": 283,
            "strongBuy": 279,
            "buy": 262,
            "hold": 284,
            "sell": 264,
            "strongSell": 264,
            "consensus": 265,
            "score": 285,
            "total": 286,
            "updated": 287
          },
          "2024-02-29",
          "Feb '24",
          9,
          4.7,
          33,
          "2024-02-28",
          {
            "date": 289,
            "month": 290,
            "strongBuy": 260,
            "buy": 262,
            "hold": 262,
            "sell": 264,
            "strongSell": 263,
            "consensus": 265,
            "score": 291,
            "total": 292,
            "updated": 293
          },
          "2024-03-31",
          "Mar '24",
          4.84,
          32,
          "2024-03-28",
          {
            "date": 295,
            "month": 296,
            "strongBuy": 262,
            "buy": 260,
            "hold": 284,
            "sell": 264,
            "strongSell": 263,
            "consensus": 265,
            "score": 291,
            "total": 189,
            "updated": 297
          },
          "2024-04-30",
          "Apr '24",
          "2024-04-29",
          {
            "date": 299,
            "month": 300,
            "strongBuy": 284,
            "buy": 260,
            "hold": 262,
            "sell": 264,
            "strongSell": 263,
            "consensus": 265,
            "score": 301,
            "total": 189,
            "updated": 302
          },
          "2024-05-31",
          "May '24",
          4.52,
          "2024-05-30",
          {
            "date": 304,
            "month": 305,
            "strongBuy": 260,
            "buy": 260,
            "hold": 306,
            "sell": 264,
            "strongSell": 263,
            "consensus": 265,
            "score": 307,
            "total": 189,
            "updated": 308
          },
          "2024-06-30",
          "Jun '24",
          8,
          5.16,
          "2024-06-28",
          {
            "date": 310,
            "month": 311,
            "strongBuy": 261,
            "buy": 284,
            "hold": 306,
            "sell": 264,
            "strongSell": 263,
            "consensus": 265,
            "score": 312,
            "total": 189,
            "updated": 313
          },
          "2024-07-31",
          "Jul '24",
          5.48,
          "2024-07-29",
          {
            "date": 315,
            "month": 316,
            "strongBuy": 261,
            "buy": 284,
            "hold": 284,
            "sell": 264,
            "strongSell": 263,
            "consensus": 265,
            "score": 317,
            "total": 292,
            "updated": 318
          },
          "2024-08-31",
          "Aug '24",
          5.31,
          "2024-08-28",
          {
            "date": 48,
            "month": 320,
            "strongBuy": 261,
            "buy": 306,
            "hold": 262,
            "sell": 264,
            "strongSell": 263,
            "consensus": 265,
            "score": 307,
            "total": 292,
            "updated": 213
          },
          "Sep '24",
          {
            "date": 196,
            "month": 322,
            "strongBuy": 261,
            "buy": 306,
            "hold": 260,
            "sell": 264,
            "strongSell": 263,
            "consensus": 265,
            "score": 323,
            "total": 286,
            "updated": 196
          },
          "Oct '24",
          5,
          [
            325,
            340,
            358,
            372,
            387
          ],
          {
            "action_rt": 326,
            "pt_now": 327,
            "pt_old": 327,
            "firm": 328,
            "analyst": 329,
            "slug": 330,
            "date": 196,
            "rating_new": 331,
            "rating_old": 331,
            "time": 332,
            "scores": 333
          },
          "Reiterates",
          225,
          "Piper Sandler",
          "Matt Farrell",
          "matt-farrell",
          "Hold",
          "07:56:32",
          {
            "success_rate": 334,
            "avg_return": 335,
            "return_pct": 336,
            "total": 40,
            "score": 337,
            "stars": 338,
            "tie_breaker": 339
          },
          42.86,
          4.79,
          45.8,
          49.83,
          3.18,
          43.82,
          {
            "action_rt": 341,
            "pt_now": 342,
            "pt_old": 343,
            "firm": 344,
            "analyst": 345,
            "slug": 346,
            "date": 347,
            "rating_new": 331,
            "rating_old": 348,
            "time": 349,
            "scores": 350
          },
          "Initiates",
          212.92,
          205,
          "Jefferies",
          "Kyle Mcnealy",
          "kyle-mcnealy",
          "2024-10-07",
          "Strong Buy",
          "09:18:03",
          {
            "success_rate": 351,
            "avg_return": 352,
            "return_pct": 353,
            "total": 354,
            "score": 355,
            "stars": 356,
            "tie_breaker": 357
          },
          72.41,
          5.89,
          48.5,
          29,
          62.84,
          1.6,
          73.59,
          {
            "action_rt": 326,
            "pt_now": 359,
            "pt_old": 359,
            "firm": 360,
            "analyst": 361,
            "slug": 362,
            "date": 206,
            "rating_new": 348,
            "rating_old": 348,
            "time": 363,
            "scores": 364
          },
          256,
          "B of A Securities",
          "Wamsi Mohan",
          "wamsi-mohan",
          "13:20:35",
          {
            "success_rate": 365,
            "avg_return": 366,
            "return_pct": 367,
            "total": 368,
            "score": 369,
            "stars": 370,
            "tie_breaker": 371
          },
          60.12,
          15.74,
          71.43,
          163,
          71.75,
          4.49,
          63.27,
          {
            "action_rt": 373,
            "pt_now": 200,
            "pt_old": 200,
            "firm": 374,
            "analyst": 375,
            "slug": 376,
            "date": 252,
            "rating_new": 377,
            "rating_old": 377,
            "time": 378,
            "scores": 379
          },
          "Maintains",
          "Barclays",
          "Tim Long",
          "tim-long",
          "Sell",
          "11:58:30",
          {
            "success_rate": 380,
            "avg_return": 381,
            "return_pct": 382,
            "total": 383,
            "score": 384,
            "stars": 385,
            "tie_breaker": 386
          },
          61.97,
          13.45,
          67.6,
          213,
          71.36,
          4.43,
          64.66,
          {
            "action_rt": 326,
            "pt_now": 327,
            "pt_old": 327,
            "firm": 388,
            "analyst": 389,
            "slug": 390,
            "date": 213,
            "rating_new": 331,
            "rating_old": 331,
            "time": 391,
            "scores": 392
          },
          "New Street Research",
          "Pierre Ferragu",
          "pierre-ferragu",
          "10:27:12",
          {
            "success_rate": 393,
            "avg_return": 394,
            "return_pct": 395,
            "total": 396,
            "score": 397,
            "stars": 398,
            "tie_breaker": 399
          },
          70,
          51.26,
          94.74,
          20,
          79.29,
          4.81,
          80.25,
          {}
        ],
        "uses": {
          "params": [
            "symbol"
          ]
        }
      }
    ]
  }